texext/__init__.py
texext/_version.py
texext/math_dollar.py
texext/mathcode.py
texext/tests/__init__.py
texext/tests/conftest.py
texext/tests/for_docstrings.py
texext/tests/test_custom_plotcontext.py
texext/tests/test_custom_plotdirective.py
texext/tests/test_docstrings.py
texext/tests/test_mathdollar.py
texext/tests/test_plotdirective.py
texext/tests/test_tinypages.py
texext/tests/plotdirective/conf.py
texext/tests/plotdirective/index.rst
texext/tests/plotdirective/plot_and_math.rst
texext/tests/plotdirective/_static/README.txt
texext/tests/tinypages/conf.py
texext/tests/tinypages/index.rst
texext/tests/tinypages/some_math.rst
texext/tests/tinypages/_static/README.txt
texext-0.6.7.dist-info/LICENSE
texext-0.6.7.dist-info/METADATA
texext-0.6.7.dist-info/WHEEL
texext-0.6.7.dist-info/top_level.txt
texext-0.6.7.dist-info/RECORD
