Metadata-Version: 2.1
Name: texext
Version: 0.6.7
Summary: Sphinx extensions for working with LaTeX math
Home-page: http://github.com/matthew-brett/texext
Author: Ondřej Čertík, Matthew Brett
Author-email: matthew.brett@gmail.com
Maintainer: Matthew Brett, Ondřej Čertík
Maintainer-email: matthew.brett@gmail.com
License: BSD license
Platform: UNKNOWN
Classifier: Development Status :: 4 - Beta
Classifier: Environment :: Console
Classifier: Intended Audience :: Developers
Classifier: Intended Audience :: Science/Research
Classifier: License :: OSI Approved :: BSD License
Classifier: Programming Language :: Python
Classifier: Programming Language :: Python :: 3
Classifier: Topic :: Scientific/Engineering
Classifier: Operating System :: Microsoft :: Windows
Classifier: Operating System :: POSIX
Classifier: Operating System :: Unix
Classifier: Operating System :: MacOS
License-File: LICENSE
Requires-Dist: sphinx (>=4)
Requires-Dist: docutils (>=0.14)
Provides-Extra: test
Requires-Dist: sympy (>=1.0) ; extra == 'test'
Requires-Dist: matplotlib (>=3.1) ; extra == 'test'
Requires-Dist: pytest ; extra == 'test'
Requires-Dist: sphinxtesters (>=0.2.3) ; extra == 'test'
